sphinxext/delta.py
sphinxext_delta-0.3.1.dist-info/LICENSE.md
sphinxext_delta-0.3.1.dist-info/METADATA
sphinxext_delta-0.3.1.dist-info/WHEEL
sphinxext_delta-0.3.1.dist-info/top_level.txt
sphinxext_delta-0.3.1.dist-info/RECORD
