Metadata-Version: 2.2
Name: sphinxext-delta
Version: 0.3.1
Summary: Sphinx extension for listing changed Sphinx articles
Home-page: https://github.com/wpilibsuite/sphinxext-delta
Author: Vasista Vovveti, Dalton Smith
Author-email: daltzsmith@gmail.com
Classifier: Environment :: Plugins
Classifier: Environment :: Web Environment
Classifier: Framework :: Sphinx :: Extension
Classifier: Intended Audience :: Developers
Classifier: License :: OSI Approved :: MIT License
Classifier: Natural Language :: English
Classifier: Operating System :: OS Independent
Classifier: Programming Language :: Python :: 3.8
Classifier: Programming Language :: Python :: 3.9
Classifier: Programming Language :: Python :: 3.10
Classifier: Programming Language :: Python :: 3.11
Classifier: Programming Language :: Python :: 3.12
Classifier: Programming Language :: Python :: 3.13
Classifier: Programming Language :: Python
Classifier: Topic :: Documentation :: Sphinx
Classifier: Topic :: Documentation
Classifier: Topic :: Software Development :: Documentation
Classifier: Topic :: Text Processing
Classifier: Topic :: Utilities
Requires-Python: >=3.8
License-File: LICENSE.md
Requires-Dist: sphinx>=5.0
Requires-Dist: six
Requires-Dist: requests
Dynamic: author
Dynamic: author-email
Dynamic: classifier
Dynamic: description
Dynamic: description-content-type
Dynamic: home-page
Dynamic: requires-dist
Dynamic: requires-python
Dynamic: summary
